biolab/__init__.py
biolab-0.1.0.dist-info/METADATA
biolab-0.1.0.dist-info/WHEEL
biolab-0.1.0.dist-info/top_level.txt
biolab-0.1.0.dist-info/RECORD
